<?xml version="1.0" encoding="utf-8"?>
<annotation>
<folder>images</folder>
<filename>5ece756d-image48.jpg</filename>
<source>
<database>MyDatabase</database>
<annotation>COCO2017</annotation>
<image>flickr</image>
<flickrid>NULL</flickrid>
<annotator>1</annotator>
</source>
<owner>
<flickrid>NULL</flickrid>
<name>Label Studio</name>
</owner>
<size>
<width>4096</width>
<height>2048</height>
<depth>3</depth>
</size>
<segmented>0</segmented>
<object>
<name>Curb Ramp</name>
<pose>Unspecified</pose>
<truncated>0</truncated>
<difficult>0</difficult>
<bndbox>
<xmin>3013</xmin>
<ymin>891</ymin>
<xmax>3080</xmax>
<ymax>914</ymax>
</bndbox>
</object>
<object>
<name>Missing Curb Ramp</name>
<pose>Unspecified</pose>
<truncated>0</truncated>
<difficult>0</difficult>
<bndbox>
<xmin>2963</xmin>
<ymin>890</ymin>
<xmax>3009</xmax>
<ymax>915</ymax>
</bndbox>
</object>
<object>
<name>Curb Ramp</name>
<pose>Unspecified</pose>
<truncated>0</truncated>
<difficult>0</difficult>
<bndbox>
<xmin>2235</xmin>
<ymin>917</ymin>
<xmax>2339</xmax>
<ymax>948</ymax>
</bndbox>
</object>
<object>
<name>Curb Ramp</name>
<pose>Unspecified</pose>
<truncated>0</truncated>
<difficult>0</difficult>
<bndbox>
<xmin>2001</xmin>
<ymin>919</ymin>
<xmax>2064</xmax>
<ymax>947</ymax>
</bndbox>
</object>
<object>
<name>Curb Ramp</name>
<pose>Unspecified</pose>
<truncated>0</truncated>
<difficult>0</difficult>
<bndbox>
<xmin>1294</xmin>
<ymin>911</ymin>
<xmax>1345</xmax>
<ymax>932</ymax>
</bndbox>
</object>
<object>
<name>Curb Ramp</name>
<pose>Unspecified</pose>
<truncated>0</truncated>
<difficult>0</difficult>
<bndbox>
<xmin>1134</xmin>
<ymin>911</ymin>
<xmax>1197</xmax>
<ymax>947</ymax>
</bndbox>
</object>
<object>
<name>Curb Ramp</name>
<pose>Unspecified</pose>
<truncated>0</truncated>
<difficult>0</difficult>
<bndbox>
<xmin>853</xmin>
<ymin>899</ymin>
<xmax>907</xmax>
<ymax>926</ymax>
</bndbox>
</object>
<object>
<name>Curb Ramp</name>
<pose>Unspecified</pose>
<truncated>0</truncated>
<difficult>0</difficult>
<bndbox>
<xmin>612</xmin>
<ymin>917</ymin>
<xmax>696</xmax>
<ymax>945</ymax>
</bndbox>
</object>
</annotation>
